gm2m_relations/__init__.py
gm2m_relations/serializers.py
gm2m_relations-1.0.3.dist-info/LICENCE
gm2m_relations-1.0.3.dist-info/METADATA
gm2m_relations-1.0.3.dist-info/WHEEL
gm2m_relations-1.0.3.dist-info/top_level.txt
gm2m_relations-1.0.3.dist-info/RECORD
