Metadata-Version: 2.1
Name: gm2m-relations
Version: 1.0.3
Summary: This library implements Django REST Framework serializers to handle generic many to many relations.
Home-page: https://github.com/mojtabaakbari221b/rest-framework-gm2m-relations
Author: mojtaba akbari
Author-email: mojtaba.akbari.221b@gmail.com
License: MIT
Platform: UNKNOWN
Requires-Python: >=3.7
License-File: LICENCE
Requires-Dist: rest-framework-generic-relations
